pdbtest/__init__.py
pdbtest/__main__.py
pdbtest/pdbtest.py
pdbtest-1.5.dist-info/LICENSE.txt
pdbtest-1.5.dist-info/METADATA
pdbtest-1.5.dist-info/WHEEL
pdbtest-1.5.dist-info/top_level.txt
pdbtest-1.5.dist-info/RECORD
