Metadata-Version: 2.1
Name: pdbtest
Version: 1.5
Summary: A unittest shim to make PDB debugging of test cases easy.
Home-page: https://github.com/zack112358/pdbtest/
Author: Zachary J. McCord
Author-email: zjmccord@gmail.com
License: UNKNOWN
Keywords: testing,pdb,unittest
Platform: UNKNOWN
Classifier: Programming Language :: Python :: 3
Classifier: Programming Language :: Python :: 2
Classifier: Topic :: Software Development :: Debuggers
Classifier: Topic :: Software Development :: Testing
Classifier: License :: OSI Approved :: Apache Software License
Classifier: Operating System :: OS Independent
